parseIdCard/__init__.py
parseIdCard/area
parseIdCard/parseIdCard.py
parseIdCard-1.0.1.dist-info/LICENSE
parseIdCard-1.0.1.dist-info/METADATA
parseIdCard-1.0.1.dist-info/WHEEL
parseIdCard-1.0.1.dist-info/top_level.txt
parseIdCard-1.0.1.dist-info/RECORD
