Metadata-Version: 2.1
Name: parseIdCard
Version: 1.0.1
Summary: 一款解析身份证的工具
Home-page: https://github.com/pangao1990/parseIdCard
Author: 潘高
Author-email: pangao1990@qq.com
License: UNKNOWN
Project-URL: Blog, https://blog.pangao.vip/%E5%8F%AF%E8%83%BD%E6%98%AFPython%E4%B8%AD%E6%9C%80%E5%A5%BD%E7%94%A8%E7%9A%84%E8%BA%AB%E4%BB%BD%E8%AF%81%E8%A7%A3%E6%9E%90%E5%B7%A5%E5%85%B7%E2%80%94parseIdCard/
Keywords: idard parse
Platform: UNKNOWN
Classifier: Programming Language :: Python :: 3
Classifier: Operating System :: OS Independent
Classifier: License :: OSI Approved :: MIT License
Requires-Python: >=3
License-File: LICENSE
